shabadoo/__init__.py
shabadoo/exceptions.py
shabadoo/shabadoo.py
shabadoo/version
shabadoo-0.1.4.dist-info/LICENSE
shabadoo-0.1.4.dist-info/METADATA
shabadoo-0.1.4.dist-info/WHEEL
shabadoo-0.1.4.dist-info/top_level.txt
shabadoo-0.1.4.dist-info/RECORD
