Metadata-Version: 2.1
Name: shabadoo
Version: 0.1.4
Summary: Very easy Bayesian regression using numpyro.
Home-page: https://github.com/nolanbconaway/shabadoo
Author: Nolan Conaway
Author-email: nolanbconaway@gmail.com
License: MIT
Keywords: bayesian,regression,mcmc
Platform: UNKNOWN
Classifier: Programming Language :: Python :: 3.6
Classifier: Programming Language :: Python :: 3.7
Classifier: Programming Language :: Python :: 3.8
Requires-Dist: numpyro (~=0.4.0)
Requires-Dist: pandas (<2.0.0,>=1.0.0)
Provides-Extra: docs
Requires-Dist: sphinx (~=2.4.4) ; extra == 'docs'
Requires-Dist: m2r ; extra == 'docs'
Requires-Dist: numpydoc ; extra == 'docs'
Provides-Extra: test
Requires-Dist: black (==19.10b0) ; extra == 'test'
Requires-Dist: pytest ; extra == 'test'
Requires-Dist: pytest-cov ; extra == 'test'
Requires-Dist: codecov ; extra == 'test'
Requires-Dist: tox ; extra == 'test'
